astromet/__init__.py
astromet/fit.py
astromet/track.py
astromet-1.0.2.dist-info/LICENSE.txt
astromet-1.0.2.dist-info/METADATA
astromet-1.0.2.dist-info/WHEEL
astromet-1.0.2.dist-info/top_level.txt
astromet-1.0.2.dist-info/RECORD
