Metadata-Version: 2.1
Name: astromet
Version: 1.0.2
Summary: One and two body astrometry
Home-page: https://github.com/zpenoyre/astromet.py
Author: Zephyr Penoyre
Author-email: zephyrpenoyre@gmail.com
License: GNU GPLv3
Platform: UNKNOWN
Requires-Dist: numpy
Requires-Dist: astropy
Requires-Dist: scipy
